django_social_user/__init__.py
django_social_user/admin.py
django_social_user/backends.py
django_social_user/exceptions.py
django_social_user/models.py
django_social_user/options.py
django_social_user/signals.py
django_social_user/urls.py
django_social_user/views.py
django_social_user/migrations/0001_initial.py
django_social_user/migrations/__init__.py
django_social_user-0.1.9.dist-info/DESCRIPTION.rst
django_social_user-0.1.9.dist-info/METADATA
django_social_user-0.1.9.dist-info/pydist.json
django_social_user-0.1.9.dist-info/RECORD
django_social_user-0.1.9.dist-info/top_level.txt
django_social_user-0.1.9.dist-info/WHEEL
