Metadata-Version: 2.0
Name: django-social-user
Version: 0.1.9
Summary: A generic system for interacting with remote APIs that need to create Django users.
Home-page: https://github.com/mattsnider/Django-Social-User
Author: Matt Snider
Author-email: admin@mattsnider.com
License: MIT
Keywords: social,user
Platform: UNKNOWN
Classifier: Programming Language :: Python
Classifier: License :: OSI Approved :: MIT License
Classifier: Operating System :: OS Independent
Classifier: Development Status :: 3 - Alpha
Classifier: Environment :: Web Environment
Classifier: Intended Audience :: Developers
Classifier: Topic :: Software Development :: Libraries :: Python Modules
Requires-Dist: django (>=1.3)
